eodal/__init__.py
eodal/__meta__.py
eodal/config/__init__.py
eodal/config/settings.py
eodal/config/stac_providers.py
eodal/core/__init__.py
eodal/core/algorithms.py
eodal/core/band.py
eodal/core/operators.py
eodal/core/raster.py
eodal/core/scene.py
eodal/core/spectral_indices.py
eodal/core/sensors/__init__.py
eodal/core/sensors/landsat.py
eodal/core/sensors/planet_scope.py
eodal/core/sensors/sentinel1.py
eodal/core/sensors/sentinel2.py
eodal/core/utils/__init__.py
eodal/core/utils/geometry.py
eodal/core/utils/raster.py
eodal/core/utils/sentinel2.py
eodal/downloader/__init__.py
eodal/downloader/planet_scope/__init__.py
eodal/downloader/planet_scope/client.py
eodal/downloader/sentinel1/__init__.py
eodal/downloader/sentinel1/creodias.py
eodal/downloader/sentinel2/__init__.py
eodal/downloader/sentinel2/copernicus.py
eodal/downloader/sentinel2/creodias.py
eodal/downloader/utils/__init__.py
eodal/downloader/utils/creodias.py
eodal/downloader/utils/unzip_datasets.py
eodal/mapper/__init__.py
eodal/mapper/feature.py
eodal/mapper/filter.py
eodal/mapper/mapper.py
eodal/metadata/__init__.py
eodal/metadata/utils.py
eodal/metadata/database/__init__.py
eodal/metadata/database/db_model.py
eodal/metadata/database/ingestion.py
eodal/metadata/database/querying.py
eodal/metadata/planet_scope/__init__.py
eodal/metadata/planet_scope/parsing.py
eodal/metadata/planet_scope/database/__init__.py
eodal/metadata/planet_scope/database/ingestion.py
eodal/metadata/planet_scope/database/querying.py
eodal/metadata/sentinel1/__init__.py
eodal/metadata/sentinel1/parsing.py
eodal/metadata/sentinel1/database/__init__.py
eodal/metadata/sentinel1/database/ingestion.py
eodal/metadata/sentinel1/database/querying.py
eodal/metadata/sentinel2/__init__.py
eodal/metadata/sentinel2/parsing.py
eodal/metadata/sentinel2/utils.py
eodal/metadata/sentinel2/database/__init__.py
eodal/metadata/sentinel2/database/ingestion.py
eodal/metadata/sentinel2/database/querying.py
eodal/metadata/stac/__init__.py
eodal-0.2.4.dist-info/LICENSE
eodal-0.2.4.dist-info/METADATA
eodal-0.2.4.dist-info/WHEEL
eodal-0.2.4.dist-info/top_level.txt
eodal-0.2.4.dist-info/RECORD
