Metadata-Version: 2.1
Name: eodal
Version: 0.2.4
Summary: The Earth Observation Data Analysis Library EOdal
Home-page: https://github.com/EOA-team/eodal
Author: Group of Crop Science, ETH Zurich & EOA-Team Agroscope Reckenholz, Zurich, Switzerland
Author-email: 
License: GNU General Public License v3
Classifier: Natural Language :: English
Classifier: Programming Language :: Python :: 3
Classifier: Operating System :: OS Independent
Classifier: Programming Language :: Python :: 3.6
Classifier: Programming Language :: Python :: 3.7
Classifier: Programming Language :: Python :: 3.8
Classifier: Programming Language :: Python :: 3.9
Classifier: Programming Language :: Python :: 3.10
Classifier: Programming Language :: Python :: 3.11
Requires-Python: >=3.8
License-File: LICENSE
Requires-Dist: pandas
Requires-Dist: geopandas
Requires-Dist: sqlalchemy
Requires-Dist: geoalchemy2
Requires-Dist: numpy
Requires-Dist: pydantic-settings
Requires-Dist: pyproj
Requires-Dist: rasterio
Requires-Dist: matplotlib
Requires-Dist: lxml
Requires-Dist: joblib
Requires-Dist: psycopg2-binary
Requires-Dist: opencv-python-headless
Requires-Dist: requests
Requires-Dist: xarray
Requires-Dist: rtree
Requires-Dist: zarr
Requires-Dist: numba
Requires-Dist: pystac-client
Requires-Dist: sentinelsat
Requires-Dist: python-dotenv
Requires-Dist: planetary-computer >=1.0.0
Requires-Dist: alive-progress
Requires-Dist: rasterstats
Requires-Dist: pyyaml
Requires-Dist: myst-parser
Requires-Dist: pyotp
